celery_flask_login/__init__.py
celery_flask_login-0.1.2.dist-info/WHEEL
celery_flask_login-0.1.2.dist-info/METADATA
celery_flask_login-0.1.2.dist-info/RECORD
