Metadata-Version: 2.1
Name: celery-flask-login
Version: 0.1.2
Summary: 
Author: David Sternlicht
Author-email: d1618033@gmail.com
Requires-Python: >=3.9,<4.0
Classifier: Programming Language :: Python :: 3
Classifier: Programming Language :: Python :: 3.9
Classifier: Programming Language :: Python :: 3.10
Classifier: Programming Language :: Python :: 3.11
Requires-Dist: Flask (>=2.2.2,<3.0.0)
Requires-Dist: Flask-Login (>=0.6.2,<0.7.0)
Requires-Dist: celery (>=5.2.7,<6.0.0)
Requires-Dist: pytest (>=7.2.0,<8.0.0)
